rexart/__init__.py
rexart/_app.py
rexart/constants.py
rexart/objects.py
rexart/pulls.py
rexart/stacks.py
rexart/utils.py
rexart-0.1.dist-info/LICENSE
rexart-0.1.dist-info/METADATA
rexart-0.1.dist-info/WHEEL
rexart-0.1.dist-info/entry_points.txt
rexart-0.1.dist-info/top_level.txt
rexart-0.1.dist-info/RECORD
