Metadata-Version: 2.1
Name: rexart
Version: 0.1
Summary: Make some art out of TRExFitter output
Home-page: https://github.com/douglasdavis/rexart
Author: Doug Davis
Author-email: ddavis@ddavis.io
License: BSD 3-clause
Platform: UNKNOWN
Classifier: Development Status :: 3 - Alpha
Classifier: Intended Audience :: Science/Research
Classifier: Operating System :: MacOS
Classifier: Operating System :: POSIX
Classifier: Operating System :: Unix
Classifier: License :: OSI Approved :: BSD License
Classifier: Programming Language :: Python
Classifier: Programming Language :: Python :: 3.7
Classifier: Topic :: Scientific/Engineering
Classifier: Topic :: Scientific/Engineering :: Physics
Requires-Python: >=3.7
Requires-Dist: uproot (>=3.8)
Requires-Dist: matplotlib (>=3.1)
Requires-Dist: pyyaml (>=5.1)
